session_filtering/__init__.py
session_filtering/apps.py
session_filtering/backends.py
session_filtering/field_mapping.py
session_filtering/models.py
session_filtering/serializers.py
session_filtering/views.py
drf_session_filtering-2.0.0.dist-info/METADATA
drf_session_filtering-2.0.0.dist-info/WHEEL
drf_session_filtering-2.0.0.dist-info/top_level.txt
drf_session_filtering-2.0.0.dist-info/RECORD
