Metadata-Version: 2.1
Name: drf-session-filtering
Version: 2.0.0
Summary: Custom Models, Serializers, Backends and Views to facilitate saving filters in sessions.
Author: IIIT
Author-email: github@iiit.pl
License: UNKNOWN
Platform: UNKNOWN
Classifier: Environment :: Web Environment
Classifier: Framework :: Django
Classifier: Intended Audience :: Developers
Classifier: Operating System :: OS Independent
Classifier: Programming Language :: Python
Classifier: Programming Language :: Python :: 3.6
Classifier: Programming Language :: Python :: 3.7
Classifier: Programming Language :: Python :: 3.8
Classifier: Programming Language :: Python :: 3.9
Requires-Dist: Django (<3,>=1.11)
Requires-Dist: djangorestframework (>=3.5)
Requires-Dist: django-filter (<2.3,>=2.0)
Requires-Dist: pytz (>=2018.7)
